CHANGELOG.md
plzpy/__init__.py
plzpy/plzpy.py
plzpy-0.1.3.dist-info/entry_points.txt
plzpy-0.1.3.dist-info/LICENSE
plzpy-0.1.3.dist-info/WHEEL
plzpy-0.1.3.dist-info/METADATA
plzpy-0.1.3.dist-info/RECORD
