Metadata-Version: 2.1
Name: plzpy
Version: 0.1.3
Summary: zip/buildings rest API for Berlin
Home-page: https://github.com/noandrea/plzpy
License: MIT
Author: Andrea Giacobino
Author-email: no.andrea@gmail.com
Requires-Python: >=3.8,<4.0
Classifier: Intended Audience :: Developers
Classifier: License :: OSI Approved :: MIT License
Classifier: Operating System :: OS Independent
Classifier: Programming Language :: Python :: 3
Classifier: Programming Language :: Python :: 3.8
Requires-Dist: flask (>=1.1.2,<2.0.0)
Requires-Dist: flask-cors (>=3.0.8,<4.0.0)
Requires-Dist: waitress (>=1.4.4,<2.0.0)
Project-URL: Repository, https://github.com/noandrea/plzpy
